nonebot_plugin_puppet/__init__.py
nonebot_plugin_puppet/handle.py
nonebot_plugin_puppet/mapping.py
nonebot_plugin_puppet/parser.py
nonebot_plugin_puppet/request.py
nonebot_plugin_puppet-0.2.2.dist-info/LICENSE
nonebot_plugin_puppet-0.2.2.dist-info/WHEEL
nonebot_plugin_puppet-0.2.2.dist-info/METADATA
nonebot_plugin_puppet-0.2.2.dist-info/RECORD
