Metadata-Version: 2.1
Name: nonebot-plugin-puppet
Version: 0.2.2
Summary: Make NoneBot your puppet
Home-page: https://github.com/Jigsaw111/nonebot_plugin_puppet
License: AGPL-3.0-only
Author: Jigsaw
Author-email: j1g5aw@foxmail.com
Requires-Python: >=3.7.3,<4.0.0
Classifier: License :: OSI Approved :: GNU Affero General Public License v3
Classifier: Programming Language :: Python :: 3
Classifier: Programming Language :: Python :: 3.8
Classifier: Programming Language :: Python :: 3.9
Classifier: Programming Language :: Python :: 3.10
Requires-Dist: nonebot-adapter-onebot (>=2.0.0-beta.1,<3.0.0)
Requires-Dist: nonebot2 (>=2.0.0-beta.1,<3.0.0)
Project-URL: Repository, https://github.com/Jigsaw111/nonebot_plugin_puppet
